VERSION
concero/__init__.py
concero/__main__.py
concero/_identifier.py
concero/cero.py
concero/conf.py
concero/fake_model.py
concero/format_convert_tools.py
concero/from_cero.py
concero/libfuncs.py
concero/libfuncs_wrappers.py
concero/main.py
concero/model.py
concero/modfuncs.py
concero/scenario.py
concero/to_cero.py
concero/doc/Makefile
concero/doc/build/html/.buildinfo
concero/doc/build/html/cero.html
concero/doc/build/html/coding_guidelines.html
concero/doc/build/html/design_philosophy.html
concero/doc/build/html/from_cero.html
concero/doc/build/html/genindex.html
concero/doc/build/html/import_guidelines.html
concero/doc/build/html/index.html
concero/doc/build/html/install_requirements.html
concero/doc/build/html/libfuncs_wrappers.html
concero/doc/build/html/models.html
concero/doc/build/html/modfuncs.html
concero/doc/build/html/objects.inv
concero/doc/build/html/py-modindex.html
concero/doc/build/html/quickstart.html
concero/doc/build/html/reference.html
concero/doc/build/html/scenarios.html
concero/doc/build/html/search.html
concero/doc/build/html/searchindex.js
concero/doc/build/html/tests.html
concero/doc/build/html/to_cero.html
concero/doc/build/html/_modules/cero.html
concero/doc/build/html/_modules/from_cero.html
concero/doc/build/html/_modules/index.html
concero/doc/build/html/_modules/libfuncs.html
concero/doc/build/html/_modules/libfuncs_wrappers.html
concero/doc/build/html/_modules/main.html
concero/doc/build/html/_modules/model.html
concero/doc/build/html/_modules/modfuncs.html
concero/doc/build/html/_modules/scenario.html
concero/doc/build/html/_modules/to_cero.html
concero/doc/build/html/_sources/cero.rst.txt
concero/doc/build/html/_sources/coding_guidelines.rst.txt
concero/doc/build/html/_sources/design_philosophy.rst.txt
concero/doc/build/html/_sources/from_cero.rst.txt
concero/doc/build/html/_sources/import_guidelines.rst.txt
concero/doc/build/html/_sources/index.rst.txt
concero-0.6.1.dist-info/METADATA
concero-0.6.1.dist-info/RECORD
concero-0.6.1.dist-info/WHEEL
concero-0.6.1.dist-info/entry_points.txt
concero-0.6.1.dist-info/top_level.txt
