Metadata-Version: 2.1
Name: concero
Version: 0.6.1
Summary: Automates the running of models and data format conversion for csv, xlsx, vd and har files.
Home-page: https://github.com/charlie0389/ConCERO
Author: Lyle Collins
Author-email: Lyle.Collins@csiro.au
License: GPL v3
Keywords: concero convert economic data har csv xlsx vd model
Platform: UNKNOWN
Requires-Python: >=3.5
Requires-Dist: pandas (>=0.23)
Requires-Dist: seaborn (>=0.8.1)
Requires-Dist: pyyaml
Requires-Dist: xlrd (>=1.1.0)
Requires-Dist: openpyxl
Requires-Dist: harpy3 (==0.3.1)
